Metadata-Version: 2.1
Name: upsonic-auth
Version: 0.2.0
Summary: The cloud authentication save system for your python applications !
Home-page: https://github.com/Upsonic/Upsonic-Auth
Author: Onur Atakan ULUSOY
Author-email: atadogan06@gmail.com
License: MIT
Platform: UNKNOWN
Requires-Python: >= 3
